{
  "main": {
    "id": "c123b627faa43e4b",
    "type": "split",
    "children": [
      {
        "id": "1b15cd32d86b8256",
        "type": "tabs",
        "children": [
          {
            "id": "47495fc299cc0ca9",
            "type": "leaf",
            "state": {
              "type": "empty",
              "state": {}
            }
          }
        ]
      }
    ],
    "direction": "vertical"
  },
  "left": {
    "id": "cb3c1fc3f684fb88",
    "type": "split",
    "children": [
      {
        "id": "4f7d6523456df080",
        "type": "tabs",
        "children": [
          {
            "id": "8a79f3414a9a1973",
            "type": "leaf",
            "state": {
              "type": "file-explorer",
              "state": {
                "sortOrder": "alphabetical"
              }
            }
          },
          {
            "id": "a1acf875de197ebe",
            "type": "leaf",
            "state": {
              "type": "search",
              "state": {
                "query": "",
                "matchingCase": false,
                "explainSearch": false,
                "collapseAll": false,
                "extraContext": false,
                "sortOrder": "alphabetical"
              }
            }
          },
          {
            "id": "c6584b1717a83105",
            "type": "leaf",
            "state": {
              "type": "starred",
              "state": {}
            }
          }
        ]
      }
    ],
    "direction": "horizontal",
    "width": 300
  },
  "right": {
    "id": "e17ec28cf815943f",
    "type": "split",
    "children": [
      {
        "id": "9eb86909b600fead",
        "type": "tabs",
        "children": [
          {
            "id": "9ad3448baf3db58f",
            "type": "leaf",
            "state": {
              "type": "backlink",
              "state": {
                "collapseAll": false,
                "extraContext": false,
                "sortOrder": "alphabetical",
                "showSearch": false,
                "searchQuery": "",
                "backlinkCollapsed": false,
                "unlinkedCollapsed": true
              }
            }
          },
          {
            "id": "9aad8da6127af973",
            "type": "leaf",
            "state": {
              "type": "outgoing-link",
              "state": {
                "linksCollapsed": false,
                "unlinkedCollapsed": true
              }
            }
          },
          {
            "id": "606a4a6c57418717",
            "type": "leaf",
            "state": {
              "type": "tag",
              "state": {
                "sortOrder": "frequency",
                "useHierarchy": true
              }
            }
          },
          {
            "id": "59e2937a79fe3b21",
            "type": "leaf",
            "state": {
              "type": "outline",
              "state": {}
            }
          }
        ]
      }
    ],
    "direction": "horizontal",
    "width": 300,
    "collapsed": true
  },
  "active": "47495fc299cc0ca9",
  "lastOpenFiles": [
    "Aziende Files.md",
    "Academia Da Leggere.md",
    "Nightdoomer Podcast/Da Approfondire/Amazon Alexa is dying.md",
    "Templates/# {{ title }}.md",
    "Untitled.md",
    "People Files.md",
    "test.md"
  ]
}